smqtk_image_io/__init__.py
smqtk_image_io/bbox.py
smqtk_image_io/impls/__init__.py
smqtk_image_io/impls/image_reader/__init__.py
smqtk_image_io/impls/image_reader/gdal_io.py
smqtk_image_io/impls/image_reader/pil_io.py
smqtk_image_io/interfaces/__init__.py
smqtk_image_io/interfaces/image_reader.py
smqtk_image_io/py.typed
smqtk_image_io/utils/__init__.py
smqtk_image_io/utils/image.py
smqtk_image_io-0.18.0.dist-info/LICENSE.txt
smqtk_image_io-0.18.0.dist-info/METADATA
smqtk_image_io-0.18.0.dist-info/WHEEL
smqtk_image_io-0.18.0.dist-info/entry_points.txt
smqtk_image_io-0.18.0.dist-info/RECORD
