Metadata-Version: 2.1
Name: smqtk_image_io
Version: 0.18.0
Summary: SMQTK Image IO
License: BSD-3-Clause
Author: Kitware, Inc.
Author-email: smqtk-developers@kitware.com
Requires-Python: >=3.10,<4.0
Classifier: Development Status :: 3 - Alpha
Classifier: Intended Audience :: Developers
Classifier: Intended Audience :: Science/Research
Classifier: License :: OSI Approved :: BSD License
Classifier: Operating System :: MacOS :: MacOS X
Classifier: Operating System :: Unix
Classifier: Programming Language :: Python :: 3
Classifier: Programming Language :: Python :: 3.10
Classifier: Programming Language :: Python :: 3.11
Classifier: Programming Language :: Python :: 3.12
Classifier: Programming Language :: Python :: 3.13
Requires-Dist: numpy (>=1.21)
Requires-Dist: pillow (>=8.2.0)
Requires-Dist: smqtk-core (>=0.20)
Requires-Dist: smqtk-dataprovider (>=0.19.0)
